{"provides":{"HTTP::Request":{"file":"lib/HTTP/Request.pm","version":6.24},"HTTP::Headers":{"file":"lib/HTTP/Headers.pm","version":6.24},"HTTP::Headers::Auth":{"file":"lib/HTTP/Headers/Auth.pm","version":6.24},"HTTP::Status":{"file":"lib/HTTP/Status.pm","version":6.24},"HTTP::Response":{"version":6.24,"file":"lib/HTTP/Response.pm"},"HTTP::Headers::Util":{"version":6.24,"file":"lib/HTTP/Headers/Util.pm"},"HTTP::Config":{"version":6.24,"file":"lib/HTTP/Config.pm"},"HTTP::Message":{"file":"lib/HTTP/Message.pm","version":6.24},"HTTP::Headers::ETag":{"version":6.24,"file":"lib/HTTP/Headers/ETag.pm"},"HTTP::Request::Common":{"version":6.24,"file":"lib/HTTP/Request/Common.pm"}},"pathname":"O/OA/OALDERS/HTTP-Message-6.24.tar.gz","dist":"HTTP-Message-6.24","name":"HTTP::Message","version":6.24,"target":"HTTP::Request"}